Metadata-Version: 1.0
Name: fzu
Version: 0.2.0
Summary: Fuzzy unicode search
Home-page: https://github.com/tebeka/fzu
Author: Miki Tebeka
Author-email: miki.tebeka@gmail.com
License: BSD
Platform: UNKNOWN
